<Gesture Name="question_mark05" Number="05" NumPts="33"><Point X="175" Y="308" /><Point X="176" Y="310" /><Point X="181" Y="315" /><Point X="195" Y="322" /><Point X="215" Y="331" /><Point X="229" Y="336" /><Point X="243" Y="341" /><Point X="254" Y="344" /><Point X="256" Y="344" /><Point X="257" Y="344" /><Point X="259" Y="342" /><Point X="259" Y="341" /><Point X="268" Y="313" /><Point X="272" Y="300" /><Point X="274" Y="277" /><Point X="275" Y="259" /><Point X="275" Y="253" /><Point X="270" Y="231" /><Point X="264" Y="219" /><Point X="255" Y="207" /><Point X="253" Y="204" /><Point X="245" Y="198" /><Point X="240" Y="194" /><Point X="237" Y="192" /><Point X="237" Y="191" /><Point X="240" Y="191" /><Point X="248" Y="191" /><Point X="262" Y="191" /><Point X="285" Y="191" /><Point X="303" Y="191" /><Point X="314" Y="191" /><Point X="322" Y="191" /><Point X="324" Y="191" /></Gesture>