<Gesture Name="triangle09" Number="09" NumPts="73"><Point X="309" Y="271" /><Point X="308" Y="271" /><Point X="303" Y="268" /><Point X="298" Y="264" /><Point X="292" Y="260" /><Point X="284" Y="255" /><Point X="278" Y="250" /><Point X="267" Y="239" /><Point X="258" Y="230" /><Point X="254" Y="226" /><Point X="248" Y="221" /><Point X="246" Y="219" /><Point X="243" Y="216" /><Point X="237" Y="212" /><Point X="234" Y="209" /><Point X="228" Y="203" /><Point X="221" Y="195" /><Point X="214" Y="187" /><Point X="207" Y="179" /><Point X="201" Y="172" /><Point X="197" Y="167" /><Point X="191" Y="162" /><Point X="189" Y="159" /><Point X="185" Y="156" /><Point X="182" Y="152" /><Point X="180" Y="151" /><Point X="180" Y="150" /><Point X="180" Y="150" /><Point X="180" Y="150" /><Point X="180" Y="150" /><Point X="180" Y="150" /><Point X="194" Y="149" /><Point X="206" Y="148" /><Point X="241" Y="146" /><Point X="264" Y="146" /><Point X="316" Y="146" /><Point X="330" Y="146" /><Point X="363" Y="148" /><Point X="374" Y="149" /><Point X="387" Y="150" /><Point X="387" Y="150" /><Point X="393" Y="151" /><Point X="396" Y="152" /><Point X="399" Y="153" /><Point X="402" Y="154" /><Point X="402" Y="154" /><Point X="402" Y="154" /><Point X="402" Y="154" /><Point X="395" Y="165" /><Point X="391" Y="169" /><Point X="380" Y="186" /><Point X="373" Y="195" /><Point X="366" Y="204" /><Point X="359" Y="213" /><Point X="353" Y="220" /><Point X="344" Y="230" /><Point X="344" Y="231" /><Point X="335" Y="242" /><Point X="330" Y="247" /><Point X="326" Y="252" /><Point X="324" Y="255" /><Point X="323" Y="257" /><Point X="323" Y="257" /><Point X="322" Y="258" /><Point X="322" Y="258" /><Point X="322" Y="258" /><Point X="319" Y="261" /><Point X="316" Y="264" /><Point X="315" Y="266" /><Point X="314" Y="267" /><Point X="314" Y="267" /><Point X="313" Y="268" /><Point X="313" Y="268" /></Gesture>